langchain_dartmouth/__init__.py
langchain_dartmouth/_version.py
langchain_dartmouth/base.py
langchain_dartmouth/cross_encoders.py
langchain_dartmouth/definitions.py
langchain_dartmouth/embeddings.py
langchain_dartmouth/exceptions.py
langchain_dartmouth/llms.py
langchain_dartmouth/model_listing.py
langchain_dartmouth/py.typed
langchain_dartmouth/utils.py
langchain_dartmouth/retrievers/__init__.py
langchain_dartmouth/retrievers/document_compressors.py
langchain_dartmouth-0.3.0.dist-info/METADATA
langchain_dartmouth-0.3.0.dist-info/WHEEL
langchain_dartmouth-0.3.0.dist-info/licenses/LICENSE
langchain_dartmouth-0.3.0.dist-info/RECORD
