Metadata-Version: 2.4
Name: langchain_dartmouth
Version: 0.3.0
Summary: LangChain components for Dartmouth-hosted models.
Project-URL: Homepage, https://github.com/Dartmouth-Libraries/langchain-dartmouth
Project-URL: Issues, https://github.com/Dartmouth-Libraries/langchain-dartmouth/issues
Author-email: Simon Stone <simon.stone@dartmouth.edu>
License: MIT License
License-File: LICENSE
Classifier: Development Status :: 4 - Beta
Classifier: License :: OSI Approved :: MIT License
Classifier: Operating System :: OS Independent
Classifier: Programming Language :: Python :: 3
Classifier: Topic :: Scientific/Engineering :: Artificial Intelligence
Requires-Python: >=3.10
Requires-Dist: dartmouth-auth
Requires-Dist: langchain
Requires-Dist: langchain-community
Requires-Dist: langchain-huggingface>=0.3.0
Requires-Dist: langchain-openai
Requires-Dist: python-dotenv
Requires-Dist: text-generation
Provides-Extra: dev
Requires-Dist: pytest; extra == 'dev'
Provides-Extra: docs
Requires-Dist: autodoc-pydantic; extra == 'docs'
Requires-Dist: sphinx; extra == 'docs'
Requires-Dist: sphinx-rtd-theme; extra == 'docs'
